Metadata-Version: 2.1
Name: stockx-parser
Version: 0.0.6
Summary: A simple parser for stockx plateform
Home-page: https://github.com/sathouel/stockx-parser.git
Author: Steven Athouel
Author-email: sathouel@gmail.com
License: UNKNOWN
Platform: UNKNOWN
Classifier: Programming Language :: Python :: 3
Classifier: License :: OSI Approved :: MIT License
Classifier: Operating System :: OS Independent
Requires-Python: >=3.7
